nwlogger/__init__.py
nwlogger/file_logger.py
nwlogger/utils/__init__.py
nwlogger/utils/openai_info.py
nwlogger/utils/text_print.py
nwlogger-0.1.6.dist-info/METADATA
nwlogger-0.1.6.dist-info/WHEEL
nwlogger-0.1.6.dist-info/top_level.txt
nwlogger-0.1.6.dist-info/RECORD
